setup.py
nonetchat/__init__.py
nonetchat-0.1.3.dist-info/LICENSE
nonetchat-0.1.3.dist-info/METADATA
nonetchat-0.1.3.dist-info/WHEEL
nonetchat-0.1.3.dist-info/top_level.txt
nonetchat-0.1.3.dist-info/RECORD
