Metadata-Version: 2.1
Name: nonetchat
Version: 0.1.3
Summary: Enables you to chat with ai locally
Author-email: Mariyala Rohith <mariyalarohith29@gmail.com>
Project-URL: Homepage, https://github.com/mrohith29/nonetchat
Project-URL: Issues, https://github.com/mrohith29/nonetchat/issues
Classifier: Programming Language :: Python :: 3
Classifier: License :: OSI Approved :: MIT License
Classifier: Operating System :: OS Independent
Requires-Python: >=3.8
License-File: LICENSE
